README.rst
setup.cfg
setup.py
fqutils/__init__.py
fqutils/fastq.py
fqutils.egg-info/PKG-INFO
fqutils.egg-info/SOURCES.txt
fqutils.egg-info/dependency_links.txt
fqutils.egg-info/not-zip-safe
fqutils.egg-info/requires.txt
fqutils.egg-info/top_level.txt