Metadata-Version: 1.2
Name: fqutils
Version: 0.0.0.dev6
Summary: fastq file utils in python
Home-page: https://github.com/yech1990/fqutils
Author: Ye Chang test
Author-email: yech1990@gmail.com
License: MIT
Keywords: ngs,bio,DNA,RNA
Platform: UNKNOWN
Requires-Python: >=3.5
